pysquirrel/__init__.py
pysquirrel/core.py
pysquirrel/data/NUTS2021-2024.yaml
pysquirrel/data/SR2021-2024.yaml
pysquirrel-1.1.dist-info/LICENSE
pysquirrel-1.1.dist-info/METADATA
pysquirrel-1.1.dist-info/WHEEL
pysquirrel-1.1.dist-info/RECORD
