Metadata-Version: 2.1
Name: pysquirrel
Version: 1.1
Summary: Python package designed to fetch NUTS administrative divisions
License: MIT
Author: Scenario Services team, ECE program, IIASA
Maintainer: David Almeida
Maintainer-email: almeida@iiasa.ac.at
Requires-Python: >=3.10,<4.0
Classifier: License :: OSI Approved :: MIT License
Classifier: Programming Language :: Python :: 3
Classifier: Programming Language :: Python :: 3.10
Classifier: Programming Language :: Python :: 3.11
Classifier: Programming Language :: Python :: 3.12
Requires-Dist: openpyxl (>=3.1.5,<4.0.0)
Requires-Dist: pydantic (>=2.8.2,<3.0.0)
Requires-Dist: pyyaml (>=6.0.2,<7.0.0)
